LICENSE
README.md
setup.py
makit/lib/_.py
makit/lib/__init__.py
makit/lib/_builtins.py
makit/lib/_doc.py
makit/lib/_error.py
makit/lib/_event.py
makit/lib/_hash.py
makit/lib/_json.py
makit/lib/_serialize.py
makit/lib/_settings.py
makit/lib/_time.py
makit/lib/attr.py
makit/lib/check.py
makit/lib/cmd.py
makit/lib/conf.py
makit/lib/const.py
makit/lib/ctx.py
makit/lib/encoding.py
makit/lib/enum.py
makit/lib/errors.py
makit/lib/fn.py
makit/lib/hook.py
makit/lib/http.py
makit/lib/jsonpath.py
makit/lib/loop.py
makit/lib/lst.py
makit/lib/net.py
makit/lib/ospath.py
makit/lib/pkg.py
makit/lib/platform.py
makit/lib/process.py
makit/lib/py.py
makit/lib/string.py
makit/lib/task.py
makit/lib/thread.py
makit/lib/uuid.py
makit/lib/validate.py
makit/lib/collections/__init__.py
makit/lib/collections/_dict.py
makit/lib/logging/__init__.py
makit/lib/logging/colors.py
makit/lib/logging/core.py
makit/lib/logging/handlers.py
makit_lib.egg-info/PKG-INFO
makit_lib.egg-info/SOURCES.txt
makit_lib.egg-info/dependency_links.txt
makit_lib.egg-info/requires.txt
makit_lib.egg-info/top_level.txt